strqa/__init__.py
strqa/main.py
strqa/objects_tester/__init__.py
strqa/objects_tester/cube_tester.py
strqa/utils/__init__.py
strqa/utils/baseline_creation.py
strqa/utils/helpers.py
strqa/utils/html_creation.py
strqa/utils/object_mapper.py
strqa/utils/sql_comparison.py
strqa/utils/types.py
strqa/utils/templates/comparison-row.html.template
strqa/utils/templates/comparison.html.template
strqa/utils/templates/templates-styling.css
strqa/utils/templates/tests-summary-table-row.html.template
strqa/utils/templates/tests-summary-table-sql-row.html.template
strqa/utils/templates/tests-summary-table.html.template
strqa/utils/templates/tests-summary.html.template
strqa_py-11.5.5.101.dist-info/METADATA
strqa_py-11.5.5.101.dist-info/WHEEL
strqa_py-11.5.5.101.dist-info/licenses/LICENSE
strqa_py-11.5.5.101.dist-info/RECORD
